hatch_containers/__about__.py
hatch_containers/__init__.py
hatch_containers/dockerfile.py
hatch_containers/hooks.py
hatch_containers/plugin.py
hatch_containers-0.7.0.dist-info/METADATA
hatch_containers-0.7.0.dist-info/WHEEL
hatch_containers-0.7.0.dist-info/entry_points.txt
hatch_containers-0.7.0.dist-info/license_files/LICENSE.txt
hatch_containers-0.7.0.dist-info/RECORD
