Metadata-Version: 2.1
Name: hatch-containers
Version: 0.7.0
Summary: Hatch plugin for Docker containers
Project-URL: Funding, https://github.com/sponsors/ofek
Project-URL: History, https://github.com/ofek/hatch-containers/blob/master/HISTORY.md
Project-URL: Issues, https://github.com/ofek/hatch-containers/issues
Project-URL: Source, https://github.com/ofek/hatch-containers
Author-email: Ofek Lev <oss@ofek.dev>
Keywords: container,docker,environment,hatch,plugin
Classifier: Development Status :: 4 - Beta
Classifier: License :: OSI Approved :: MIT License
Classifier: Programming Language :: Python
Classifier: Programming Language :: Python :: 3.10
Classifier: Programming Language :: Python :: 3.7
Classifier: Programming Language :: Python :: 3.8
Classifier: Programming Language :: Python :: 3.9
Classifier: Programming Language :: Python :: Implementation :: CPython
Classifier: Programming Language :: Python :: Implementation :: PyPy
Requires-Python: >=3.7
Requires-Dist: hatch>=1.2.0
